{
	"name": "api_to_adls_jsonformat",
	"properties": {
		"description": "This format works with the delta lake",
		"activities": [
			{
				"name": "api_to_adls",
				"type": "Copy",
				"dependsOn": [],
				"policy": {
					"timeout": "0.12:00:00",
					"retry": 0,
					"retryIntervalInSeconds": 30,
					"secureOutput": false,
					"secureInput": false
				},
				"userProperties": [],
				"typeProperties": {
					"source": {
						"type": "JsonSource",
						"storeSettings": {
							"type": "HttpReadSettings",
							"requestMethod": "GET"
						},
						"formatSettings": {
							"type": "JsonReadSettings"
						}
					},
					"sink": {
						"type": "JsonSink",
						"storeSettings": {
							"type": "AzureBlobFSWriteSettings"
						},
						"formatSettings": {
							"type": "JsonWriteSettings"
						}
					},
					"enableStaging": false
				},
				"inputs": [
					{
						"referenceName": "Json1",
						"type": "DatasetReference"
					}
				],
				"outputs": [
					{
						"referenceName": "Json2",
						"type": "DatasetReference"
					}
				]
			}
		],
		"annotations": [],
		"lastPublishTime": "2023-01-31T12:29:08Z"
	},
	"type": "Microsoft.DataFactory/factories/pipelines"
}